{
  "generated_at": "2026-07-24T00:00:26-04:00",
  "cohort_rebalanced_at": "2026-07-20",
  "cohort_rebalanced_timestamp": "2026-07-20T01:26:32-04:00",
  "index_score": -0.292165,
  "leverage_dampening": false,
  "cohort_stats": {
    "total_equity": 420786340.1,
    "total_wallets": 100,
    "active_wallets": 100,
    "gross_long_usd": 715221590.16,
    "gross_short_usd": 1261570297.61,
    "net_usd": -546348707.45,
    "gross_notional_usd": 1976791887.77,
    "L_cohort_total": 4.6979
  },
  "assets": [
    {
      "asset": "BTC",
      "long_usd": 185280783.61,
      "short_usd": 401359128.07,
      "net_usd": -216078344.47,
      "tilt": -0.3683,
      "position_count": 56,
      "long_count": 20,
      "short_count": 36,
      "L_net_margin": -3.433755,
      "L_net_equity": -0.513511,
      "conv_equity": -0.3353,
      "free": true
    },
    {
      "asset": "HYPE",
      "long_usd": 117885050.82,
      "short_usd": 268591195.74,
      "net_usd": -150706144.92,
      "tilt": -0.3899,
      "position_count": 55,
      "long_count": 11,
      "short_count": 44,
      "L_net_margin": -2.111771,
      "L_net_equity": -0.358154,
      "conv_equity": -0.4954,
      "free": true
    },
    {
      "asset": "ETH",
      "long_usd": 348894193.73,
      "short_usd": 418335193.23,
      "net_usd": -69440999.5,
      "tilt": -0.0905,
      "position_count": 52,
      "long_count": 16,
      "short_count": 36,
      "L_net_margin": -0.622585,
      "L_net_equity": -0.165027,
      "conv_equity": -0.0732,
      "free": true
    },
    {
      "asset": "SOL",
      "long_usd": 19157292.05,
      "short_usd": 62177440.65,
      "net_usd": -43020148.6,
      "tilt": -0.5289,
      "position_count": 32,
      "long_count": 13,
      "short_count": 19,
      "L_net_margin": -2.698884,
      "L_net_equity": -0.102238,
      "conv_equity": -0.352,
      "free": true
    },
    {
      "asset": "LIT",
      "long_usd": 0.0,
      "short_usd": 16133481.57,
      "net_usd": -16133481.57,
      "tilt": -1.0,
      "position_count": 18,
      "long_count": 0,
      "short_count": 18,
      "L_net_margin": -3.086493,
      "L_net_equity": -0.038341,
      "conv_equity": -1.0,
      "free": true
    },
    {
      "asset": "NEAR",
      "long_usd": 1564825.5,
      "short_usd": 11732663.32,
      "net_usd": -10167837.82,
      "tilt": -0.7646,
      "position_count": 18,
      "long_count": 6,
      "short_count": 12,
      "L_net_margin": -5.471787,
      "L_net_equity": -0.024164,
      "conv_equity": -0.6946,
      "free": false
    },
    {
      "asset": "WLD",
      "long_usd": 3259.06,
      "short_usd": 5726810.54,
      "net_usd": -5723551.49,
      "tilt": -0.9989,
      "position_count": 9,
      "long_count": 1,
      "short_count": 8,
      "L_net_margin": -8.690091,
      "L_net_equity": -0.013602,
      "conv_equity": -0.9989,
      "free": false
    },
    {
      "asset": "FARTCOIN",
      "long_usd": 1552.6,
      "short_usd": 5369718.24,
      "net_usd": -5368165.64,
      "tilt": -0.9994,
      "position_count": 13,
      "long_count": 2,
      "short_count": 11,
      "L_net_margin": -4.218137,
      "L_net_equity": -0.012757,
      "conv_equity": -0.998,
      "free": false
    },
    {
      "asset": "AAVE",
      "long_usd": 7232501.19,
      "short_usd": 11658894.9,
      "net_usd": -4426393.71,
      "tilt": -0.2343,
      "position_count": 10,
      "long_count": 3,
      "short_count": 7,
      "L_net_margin": -2.343074,
      "L_net_equity": -0.010519,
      "conv_equity": -0.1246,
      "free": false
    },
    {
      "asset": "PUMP",
      "long_usd": 210054.48,
      "short_usd": 4415457.17,
      "net_usd": -4205402.68,
      "tilt": -0.9092,
      "position_count": 14,
      "long_count": 4,
      "short_count": 10,
      "L_net_margin": -6.739596,
      "L_net_equity": -0.009994,
      "conv_equity": -0.9219,
      "free": false
    },
    {
      "asset": "GRAM",
      "long_usd": 0.0,
      "short_usd": 3595377.98,
      "net_usd": -3595377.98,
      "tilt": -1.0,
      "position_count": 4,
      "long_count": 0,
      "short_count": 4,
      "L_net_margin": -5.0,
      "L_net_equity": -0.008544,
      "conv_equity": -1.0,
      "free": false
    },
    {
      "asset": "XRP",
      "long_usd": 5865376.78,
      "short_usd": 2505252.65,
      "net_usd": 3360124.13,
      "tilt": 0.4014,
      "position_count": 12,
      "long_count": 6,
      "short_count": 6,
      "L_net_margin": 0.721689,
      "L_net_equity": 0.007985,
      "conv_equity": 0.2718,
      "free": false
    },
    {
      "asset": "PAXG",
      "long_usd": 898999.57,
      "short_usd": 4216608.48,
      "net_usd": -3317608.91,
      "tilt": -0.6485,
      "position_count": 10,
      "long_count": 3,
      "short_count": 7,
      "L_net_margin": -2.143373,
      "L_net_equity": -0.007884,
      "conv_equity": -0.8354,
      "free": false
    },
    {
      "asset": "ASTER",
      "long_usd": 0.0,
      "short_usd": 2883890.05,
      "net_usd": -2883890.05,
      "tilt": -1.0,
      "position_count": 12,
      "long_count": 0,
      "short_count": 12,
      "L_net_margin": -4.357498,
      "L_net_equity": -0.006854,
      "conv_equity": -1.0,
      "free": false
    },
    {
      "asset": "ZEC",
      "long_usd": 9095717.91,
      "short_usd": 11419140.53,
      "net_usd": -2323422.61,
      "tilt": -0.1133,
      "position_count": 18,
      "long_count": 6,
      "short_count": 12,
      "L_net_margin": -0.716299,
      "L_net_equity": -0.005522,
      "conv_equity": -0.2674,
      "free": false
    },
    {
      "asset": "MON",
      "long_usd": 0.0,
      "short_usd": 2118238.57,
      "net_usd": -2118238.57,
      "tilt": -1.0,
      "position_count": 7,
      "long_count": 0,
      "short_count": 7,
      "L_net_margin": -4.539979,
      "L_net_equity": -0.005034,
      "conv_equity": -1.0,
      "free": false
    },
    {
      "asset": "LINK",
      "long_usd": 4364037.17,
      "short_usd": 2656622.78,
      "net_usd": 1707414.38,
      "tilt": 0.2432,
      "position_count": 11,
      "long_count": 4,
      "short_count": 7,
      "L_net_margin": 0.81706,
      "L_net_equity": 0.004058,
      "conv_equity": -0.247,
      "free": false
    },
    {
      "asset": "SUI",
      "long_usd": 1809794.59,
      "short_usd": 287403.58,
      "net_usd": 1522391.02,
      "tilt": 0.7259,
      "position_count": 8,
      "long_count": 4,
      "short_count": 4,
      "L_net_margin": 7.259166,
      "L_net_equity": 0.003618,
      "conv_equity": 0.601,
      "free": false
    },
    {
      "asset": "KPEPE",
      "long_usd": 27860.0,
      "short_usd": 1377115.15,
      "net_usd": -1349255.15,
      "tilt": -0.9603,
      "position_count": 4,
      "long_count": 1,
      "short_count": 3,
      "L_net_margin": -9.603409,
      "L_net_equity": -0.003207,
      "conv_equity": -0.9312,
      "free": false
    },
    {
      "asset": "TAO",
      "long_usd": 28435.87,
      "short_usd": 1329337.03,
      "net_usd": -1300901.17,
      "tilt": -0.9581,
      "position_count": 8,
      "long_count": 1,
      "short_count": 7,
      "L_net_margin": -4.79057,
      "L_net_equity": -0.003092,
      "conv_equity": -0.9432,
      "free": false
    },
    {
      "asset": "CASHCAT",
      "long_usd": 411035.69,
      "short_usd": 1559291.14,
      "net_usd": -1148255.45,
      "tilt": -0.5828,
      "position_count": 13,
      "long_count": 2,
      "short_count": 11,
      "L_net_margin": -0.194723,
      "L_net_equity": -0.002729,
      "conv_equity": -0.6298,
      "free": false
    },
    {
      "asset": "ZRO",
      "long_usd": 0.0,
      "short_usd": 1072743.95,
      "net_usd": -1072743.95,
      "tilt": -1.0,
      "position_count": 7,
      "long_count": 0,
      "short_count": 7,
      "L_net_margin": -5.0,
      "L_net_equity": -0.002549,
      "conv_equity": -1.0,
      "free": false
    },
    {
      "asset": "LTC",
      "long_usd": 0.0,
      "short_usd": 946051.28,
      "net_usd": -946051.28,
      "tilt": -1.0,
      "position_count": 7,
      "long_count": 0,
      "short_count": 7,
      "L_net_margin": -9.840832,
      "L_net_equity": -0.002248,
      "conv_equity": -1.0,
      "free": false
    },
    {
      "asset": "BNB",
      "long_usd": 673620.28,
      "short_usd": 1608999.68,
      "net_usd": -935379.39,
      "tilt": -0.4098,
      "position_count": 13,
      "long_count": 2,
      "short_count": 11,
      "L_net_margin": -3.829944,
      "L_net_equity": -0.002223,
      "conv_equity": -0.5878,
      "free": false
    },
    {
      "asset": "KBONK",
      "long_usd": 0.0,
      "short_usd": 882440.86,
      "net_usd": -882440.86,
      "tilt": -1.0,
      "position_count": 3,
      "long_count": 0,
      "short_count": 3,
      "L_net_margin": -10.0,
      "L_net_equity": -0.002097,
      "conv_equity": -1.0,
      "free": false
    },
    {
      "asset": "UNI",
      "long_usd": 253529.23,
      "short_usd": 1106420.69,
      "net_usd": -852891.46,
      "tilt": -0.6271,
      "position_count": 10,
      "long_count": 2,
      "short_count": 8,
      "L_net_margin": -6.271492,
      "L_net_equity": -0.002027,
      "conv_equity": -0.5975,
      "free": false
    },
    {
      "asset": "ADA",
      "long_usd": 776477.45,
      "short_usd": 0.0,
      "net_usd": 776477.45,
      "tilt": 1.0,
      "position_count": 4,
      "long_count": 4,
      "short_count": 0,
      "L_net_margin": 9.999497,
      "L_net_equity": 0.001845,
      "conv_equity": 1.0,
      "free": false
    },
    {
      "asset": "ENA",
      "long_usd": 844609.46,
      "short_usd": 1538373.55,
      "net_usd": -693764.08,
      "tilt": -0.2911,
      "position_count": 10,
      "long_count": 3,
      "short_count": 7,
      "L_net_margin": -0.970099,
      "L_net_equity": -0.001649,
      "conv_equity": -0.6371,
      "free": false
    },
    {
      "asset": "XMR",
      "long_usd": 159764.86,
      "short_usd": 785443.58,
      "net_usd": -625678.72,
      "tilt": -0.6619,
      "position_count": 5,
      "long_count": 1,
      "short_count": 4,
      "L_net_margin": -3.309739,
      "L_net_equity": -0.001487,
      "conv_equity": -0.6766,
      "free": false
    },
    {
      "asset": "MEGA",
      "long_usd": 0.0,
      "short_usd": 575951.04,
      "net_usd": -575951.04,
      "tilt": -1.0,
      "position_count": 6,
      "long_count": 0,
      "short_count": 6,
      "L_net_margin": -2.947021,
      "L_net_equity": -0.001369,
      "conv_equity": -1.0,
      "free": false
    },
    {
      "asset": "DOT",
      "long_usd": 496649.55,
      "short_usd": 9474.19,
      "net_usd": 487175.35,
      "tilt": 0.9626,
      "position_count": 3,
      "long_count": 2,
      "short_count": 1,
      "L_net_margin": 9.625617,
      "L_net_equity": 0.001158,
      "conv_equity": 0.9042,
      "free": false
    },
    {
      "asset": "VIRTUAL",
      "long_usd": 0.0,
      "short_usd": 446405.28,
      "net_usd": -446405.28,
      "tilt": -1.0,
      "position_count": 5,
      "long_count": 0,
      "short_count": 5,
      "L_net_margin": -5.0,
      "L_net_equity": -0.001061,
      "conv_equity": -1.0,
      "free": false
    },
    {
      "asset": "ONDO",
      "long_usd": 746733.67,
      "short_usd": 315958.89,
      "net_usd": 430774.77,
      "tilt": 0.4054,
      "position_count": 5,
      "long_count": 2,
      "short_count": 3,
      "L_net_margin": 0.580619,
      "L_net_equity": 0.001024,
      "conv_equity": 0.3185,
      "free": false
    },
    {
      "asset": "AVAX",
      "long_usd": 614931.91,
      "short_usd": 216955.8,
      "net_usd": 397976.11,
      "tilt": 0.4784,
      "position_count": 9,
      "long_count": 3,
      "short_count": 6,
      "L_net_margin": 4.784012,
      "L_net_equity": 0.000946,
      "conv_equity": 0.4212,
      "free": false
    },
    {
      "asset": "APEX",
      "long_usd": 0.0,
      "short_usd": 392525.68,
      "net_usd": -392525.68,
      "tilt": -1.0,
      "position_count": 4,
      "long_count": 0,
      "short_count": 4,
      "L_net_margin": -3.0,
      "L_net_equity": -0.000933,
      "conv_equity": -1.0,
      "free": false
    },
    {
      "asset": "XPL",
      "long_usd": 1331456.81,
      "short_usd": 1704291.14,
      "net_usd": -372834.33,
      "tilt": -0.1228,
      "position_count": 10,
      "long_count": 2,
      "short_count": 8,
      "L_net_margin": -0.677265,
      "L_net_equity": -0.000886,
      "conv_equity": -0.1602,
      "free": false
    },
    {
      "asset": "BCH",
      "long_usd": 91748.75,
      "short_usd": 397622.95,
      "net_usd": -305874.2,
      "tilt": -0.625,
      "position_count": 4,
      "long_count": 1,
      "short_count": 3,
      "L_net_margin": -6.250345,
      "L_net_equity": -0.000727,
      "conv_equity": -0.855,
      "free": false
    },
    {
      "asset": "MORPHO",
      "long_usd": 0.0,
      "short_usd": 294842.68,
      "net_usd": -294842.68,
      "tilt": -1.0,
      "position_count": 1,
      "long_count": 0,
      "short_count": 1,
      "L_net_margin": -5.0,
      "L_net_equity": -0.000701,
      "conv_equity": -1.0,
      "free": false
    },
    {
      "asset": "DOGE",
      "long_usd": 415349.08,
      "short_usd": 701837.48,
      "net_usd": -286488.4,
      "tilt": -0.2564,
      "position_count": 7,
      "long_count": 2,
      "short_count": 5,
      "L_net_margin": -2.564374,
      "L_net_equity": -0.000681,
      "conv_equity": -0.3532,
      "free": false
    },
    {
      "asset": "JUP",
      "long_usd": 0.0,
      "short_usd": 271380.89,
      "net_usd": -271380.89,
      "tilt": -1.0,
      "position_count": 1,
      "long_count": 0,
      "short_count": 1,
      "L_net_margin": -10.0,
      "L_net_equity": -0.000645,
      "conv_equity": -1.0,
      "free": false
    },
    {
      "asset": "MNT",
      "long_usd": 0.0,
      "short_usd": 260559.81,
      "net_usd": -260559.81,
      "tilt": -1.0,
      "position_count": 3,
      "long_count": 0,
      "short_count": 3,
      "L_net_margin": -5.0,
      "L_net_equity": -0.000619,
      "conv_equity": -1.0,
      "free": false
    },
    {
      "asset": "XLM",
      "long_usd": 76982.52,
      "short_usd": 284744.2,
      "net_usd": -207761.68,
      "tilt": -0.5744,
      "position_count": 3,
      "long_count": 1,
      "short_count": 2,
      "L_net_margin": -2.871805,
      "L_net_equity": -0.000494,
      "conv_equity": -0.6857,
      "free": false
    },
    {
      "asset": "VVV",
      "long_usd": 1681891.98,
      "short_usd": 1889643.52,
      "net_usd": -207751.54,
      "tilt": -0.0582,
      "position_count": 11,
      "long_count": 2,
      "short_count": 9,
      "L_net_margin": -0.174506,
      "L_net_equity": -0.000494,
      "conv_equity": -0.3715,
      "free": false
    },
    {
      "asset": "WLFI",
      "long_usd": 1001909.01,
      "short_usd": 817301.15,
      "net_usd": 184607.86,
      "tilt": 0.1015,
      "position_count": 6,
      "long_count": 3,
      "short_count": 3,
      "L_net_margin": 0.248168,
      "L_net_equity": 0.000439,
      "conv_equity": -0.0963,
      "free": false
    },
    {
      "asset": "PURR",
      "long_usd": 823325.38,
      "short_usd": 987286.28,
      "net_usd": -163960.9,
      "tilt": -0.0906,
      "position_count": 5,
      "long_count": 1,
      "short_count": 4,
      "L_net_margin": -0.271667,
      "L_net_equity": -0.00039,
      "conv_equity": -0.3364,
      "free": false
    },
    {
      "asset": "APT",
      "long_usd": 323436.85,
      "short_usd": 424987.59,
      "net_usd": -101550.73,
      "tilt": -0.1357,
      "position_count": 5,
      "long_count": 2,
      "short_count": 3,
      "L_net_margin": -1.35686,
      "L_net_equity": -0.000241,
      "conv_equity": 0.5645,
      "free": false
    },
    {
      "asset": "LDO",
      "long_usd": 691356.72,
      "short_usd": 627544.14,
      "net_usd": 63812.58,
      "tilt": 0.0484,
      "position_count": 3,
      "long_count": 1,
      "short_count": 2,
      "L_net_margin": 0.078119,
      "L_net_equity": 0.000152,
      "conv_equity": -0.1465,
      "free": false
    }
  ],
  "wallet_distribution": {
    "schema_version": 2,
    "privacy": "fixed_usd_buckets",
    "total_wallets": 100,
    "position": [
      {
        "label": "< -$100M",
        "count": 3,
        "direction": "short"
      },
      {
        "label": "-$100M to -$50M",
        "count": 3,
        "direction": "short"
      },
      {
        "label": "-$50M to -$25M",
        "count": 5,
        "direction": "short"
      },
      {
        "label": "-$25M to -$10M",
        "count": 16,
        "direction": "short"
      },
      {
        "label": "-$10M to -$5M",
        "count": 10,
        "direction": "short"
      },
      {
        "label": "-$5M to $0",
        "count": 31,
        "direction": "short"
      },
      {
        "label": "$0 to $5M",
        "count": 11,
        "direction": "long"
      },
      {
        "label": "$5M to $10M",
        "count": 3,
        "direction": "long"
      },
      {
        "label": "$10M to $25M",
        "count": 9,
        "direction": "long"
      },
      {
        "label": "$25M to $50M",
        "count": 4,
        "direction": "long"
      },
      {
        "label": "$50M to $100M",
        "count": 5,
        "direction": "long"
      },
      {
        "label": "> $100M",
        "count": 0,
        "direction": "long"
      }
    ],
    "equity": [
      {
        "label": "< $500K",
        "count": 23,
        "direction": "equity"
      },
      {
        "label": "$500K to $1M",
        "count": 15,
        "direction": "equity"
      },
      {
        "label": "$1M to $2.5M",
        "count": 26,
        "direction": "equity"
      },
      {
        "label": "$2.5M to $5M",
        "count": 20,
        "direction": "equity"
      },
      {
        "label": "$5M to $10M",
        "count": 4,
        "direction": "equity"
      },
      {
        "label": "$10M to $25M",
        "count": 10,
        "direction": "equity"
      },
      {
        "label": "$25M to $50M",
        "count": 1,
        "direction": "equity"
      },
      {
        "label": "$50M to $100M",
        "count": 1,
        "direction": "equity"
      },
      {
        "label": "> $100M",
        "count": 0,
        "direction": "equity"
      }
    ]
  }
}
